{
				"图片": "data-src=\"&&\"",
				"简介": "剧情：</span>&&</p >",
				"线路数组": "class=\"module-tab-item tab-item&&</div>",
				"线<路标题": ">&&</span>",
				"嗅探词":".m3u8",
				"跳转播放链接": "var vid=*var now=\"&&\"",
				"播放数组": "class=\"module-blocklist&&</div>",
				"搜索url": "https://www.88ysyy.com/search.php;post;searchword={wd}",
				"分类url": "https://www.88ysyy.com/search.php?page={catePg}&searchtype=5&order={by}&tid={cateId}&area={area}&year={year}&letter={letter}&yuyan={lang}&state=&money=&ver=&jq={class}",
				"分类": "电影&电视剧&综艺&动漫",
				"分类值": "1&2&3&4"
			}