{
				"主页url": "http://www.vipz8.com/",
				"请求头": "User-Agent$Mozilla/5.0 (Linux; U; Android 2.3; en-us) AppleWebKit/999+ (KHTML, like Gecko) Safari/999.9",
				"分类url": "/{cateId}_{class}_{year}_{area}__{by}_{catePg}.html;;ak",
				"分类": "电影$movie#电视剧$tv#综艺$zongyi#动漫$dongman",
				"数组": "<li class=\"col-md-* col-sm-* col-xs&&</li",
				"图片": "data-original=\"&&\"",
				"标题": "title=\"&&\"",
				"副标题": "pic-tag pic-tag-b\"&&</span>",
				"链接": "http://www.vipz8.com/+href=\"&&\"",
				"简介": "简介：&&</div",
				"搜索url": "http://www.vipz8.com/seacher-{wd}.html",
				"搜索数组": "v-thumb stui-vodlist__thumb lazyload&&</li",
				"搜索图片": "data-original=\"&&\"",
				"搜索标题": "title=\"&&\"",
				"搜索链接": "http://www.vipz8.com/+href=\"&&\"",
				"线路数组": "<h3 class=\"title\">&&/h3>",
				"线路标题": "/svg>&&<",
				"线路链接": "href=\"&&\"",
				"播放数组": "id=\"playlist&&</ul>",
				"播放列表": "<li&&</li",
				"播放标题": ">&&</a",
				"播放链接": "href=\"&&\"",
				"剧情": "[替换:伦理>>空]",
				"排序": "最近热映$rankhot#最新上映$ranklatest#最受好评$rankpoint"
			}