 {
				"主页url": "https://lkvod.me",
			"数组": "<div class=\"public-list-box public-pic-b [swiper]&&</div></div></div>",
				"图片": "data-src=\"&&\"",
				"标题": "title=\"&&\"",
				"链接": "href=\"&&\"",
				"副标题": "public-list-subtitle cor5 hide ft2\">&&",
				"简介": "<div id=\"height_limit\" class=\"text cor3\">&&</div>",
				"线路数组": "<i class=\"fa ds-dianying\"&&</a>",
				"线路标题": "💢简影👉+>&nbsp;&&<",
				"分类url": "https://lkvod.me/show/{cateId}--{by}------{catePg}---{year}.html",
				"分类": "电影$1#连续剧$2#综艺$3#动漫$4"
			}